vocabraille/__init__.py
vocabraille/vocabraille.py
vocabraille/bin/32/SAAPI32.dll
vocabraille/bin/32/UniversalSpeech.dll
vocabraille/bin/32/UniversalSpeech.tlb
vocabraille/bin/32/ZDSRAPI.dll
vocabraille/bin/32/dolapi.dll
vocabraille/bin/32/jfwapi.dll
vocabraille/bin/32/nvdaControllerClient.dll
vocabraille/bin/64/UniversalSpeech.dll
vocabraille/bin/64/ZDSRAPI.dll
vocabraille/bin/64/nvdaControllerClient.dll
vocabraille-0.1.0.dist-info/METADATA
vocabraille-0.1.0.dist-info/WHEEL
vocabraille-0.1.0.dist-info/licenses/LICENSE
vocabraille-0.1.0.dist-info/RECORD
